{"type":"Scene","props":{"width":750,"name":"combatScene","height":1334},"compId":2,"child":[{"type":"Sprite","props":{"y":0,"x":0,"width":750,"texture":"custom/bg.png","name":"background","height":1700},"compId":6},{"type":"Sprite","props":{"y":468,"x":5,"width":750,"texture":"custom/bg_effect_flare.png","name":"flare","height":750},"compId":9},{"type":"Sprite","props":{"y":938,"x":51,"width":290,"name":"missionBoard","height":290},"compId":7,"child":[{"type":"Sprite","props":{"y":0,"x":0,"width":290,"texture":"custom/popup_base.png","height":290},"compId":81,"child":[{"type":"Script","props":{"y":0,"x":0,"offY":4,"offX":0,"color":"#9a8b8b","blur":"5","runtime":"laya.effect.GlowFilterSetter"},"compId":73}]},{"type":"Sprite","props":{"y":-18.5,"x":44,"width":200,"texture":"custom/popup_header.png","scaleY":1,"scaleX":1,"name":"popup_head","height":45},"compId":12},{"type":"Text","props":{"y":22.5,"x":70,"width":154,"valign":"middle","text":"任 务","name":"text","height":60,"fontSize":34,"font":"Microsoft YaHei","color":"#195c9a","bold":true,"align":"center","runtime":"laya.display.Text"},"compId":37},{"type":"View","props":{"width":224,"name":"missionView","height":157,"centerY":35,"centerX":2},"compId":38,"child":[{"type":"Script","props":{"task01":"@Prefab:combat/task01.prefab","runtime":"combat/MissionView.ts"},"compId":68}]}]},{"type":"Sprite","props":{"y":938,"x":398,"width":290,"name":"scoreBoard","height":290},"compId":8,"child":[{"type":"Sprite","props":{"y":0,"x":0,"width":290,"texture":"custom/popup_base.png","height":290},"compId":79,"child":[{"type":"Script","props":{"offY":4,"offX":0,"color":"#9a8b8b","blur":"4","runtime":"laya.effect.GlowFilterSetter"},"compId":80}]},{"type":"Sprite","props":{"y":50,"x":2,"width":303,"texture":"custom/inGameCounter_bar.png","name":"redBar","height":63},"compId":11,"child":[{"type":"Text","props":{"y":3,"x":73,"width":154,"valign":"middle","text":"轮   剩余","name":"text","height":60,"fontSize":40,"font":"Microsoft YaHei","color":"#FFFEFE","bold":true,"align":"center","runtime":"laya.display.Text"},"compId":23}]},{"type":"Sprite","props":{"y":19,"x":-50,"texture":"custom/inGame_counter.png","name":"yellowTube"},"compId":10,"child":[{"type":"Text","props":{"y":34.25,"x":28.75,"width":71,"valign":"middle","text":"99","name":"text","height":60,"fontSize":48,"font":"Arial","color":"#FF0000","bold":true,"align":"center","runtime":"laya.display.Text"},"compId":24}]},{"type":"Sprite","props":{"y":126,"x":20,"width":249,"texture":"custom/inGameBankBalance_bar_1.png","name":"whiteBoard","height":68},"compId":16,"child":[{"type":"Text","props":{"y":1,"x":10,"width":225,"valign":"middle","text":"99999999","name":"text","height":60,"fontSize":48,"font":"Arial","color":"#343434","bold":true,"align":"right","runtime":"laya.display.Text"},"compId":25}]},{"type":"Button","props":{"y":181,"x":-3,"width":120,"stateNum":1,"skin":"custom/button_replay01.png","name":"btnReplay","height":115},"compId":18},{"type":"Button","props":{"y":201,"x":110.5,"width":63,"stateNum":2,"skin":"custom/button_info_double.png","name":"btnInfo","height":75},"compId":19},{"type":"Button","props":{"y":201,"x":198,"width":63,"stateNum":2,"skin":"custom/button_audioUnMute_double.png","name":"btnMute","height":75},"compId":20},{"type":"Sprite","props":{"y":-19,"x":45,"width":200,"texture":"custom/popup_header.png","scaleY":1,"scaleX":1,"name":"popup_head","height":45},"compId":22},{"type":"Script","props":{"runtime":"combat/ScoreBoard.ts"},"compId":41}]},{"type":"View","props":{"y":166,"x":69,"width":612,"name":"playGround","height":728},"compId":30,"child":[{"type":"Script","props":{"runtime":"combat/Playground.ts"},"compId":34}]},{"type":"Sprite","props":{"y":0,"x":0,"width":750,"texture":"custom/bgProtect.png","name":"coverBg","height":108},"compId":93},{"type":"View","props":{"y":54,"x":132,"width":610,"name":"timeBar","height":100},"compId":82,"child":[{"type":"Sprite","props":{"y":9,"x":2,"width":580,"texture":"custom/emptyTimeBar.png","name":"empty","height":76},"compId":87,"child":[{"type":"Script","props":{"y":0,"x":0,"offY":4,"offX":0,"color":"#9a8b8b","blur":"4","runtime":"laya.effect.GlowFilterSetter"},"compId":88}]},{"type":"Sprite","props":{"y":30,"x":67,"width":420,"texture":"custom/fullTimeBar.png","name":"full","height":35},"compId":90},{"type":"Script","props":{"runtime":"combat/TimeBar.ts"},"compId":95},{"type":"Sprite","props":{"y":17,"x":14,"width":50,"name":"bomb","height":50},"compId":96}]},{"type":"Script","props":{"y":18,"x":37,"runtime":"combat/Combat.ts"},"compId":105},{"type":"Button","props":{"y":65,"x":22,"width":90,"stateNum":2,"skin":"custom/button_9slice_double.png","name":"btnRefresh","height":78},"compId":108,"child":[{"type":"Text","props":{"y":19,"x":13,"text":"刷新","name":"text","fontSize":32,"font":"Microsoft YaHei","color":"#000000","bold":true,"runtime":"laya.display.Text"},"compId":109}]}],"loadList":["custom/bg.png","custom/bg_effect_flare.png","custom/popup_base.png","custom/popup_header.png","combat/task01.prefab","custom/inGameCounter_bar.png","custom/inGame_counter.png","custom/inGameBankBalance_bar_1.png","custom/button_replay01.png","custom/button_info_double.png","custom/button_audioUnMute_double.png","custom/bgProtect.png","custom/emptyTimeBar.png","custom/fullTimeBar.png","custom/button_9slice_double.png"],"loadList3D":[]}